pippi/__init__.py
pippi/text_cleaning.py
pippi/text_transformation.py
pippi/utils.py
src/__init__.py
src/text_cleaning.py
src/text_transformation.py
src/utils.py
pippi_lang-0.0.2.dist-info/METADATA
pippi_lang-0.0.2.dist-info/WHEEL
pippi_lang-0.0.2.dist-info/top_level.txt
pippi_lang-0.0.2.dist-info/RECORD
