Metadata-Version: 2.1
Name: pippi-lang
Version: 0.0.2
Summary: A simple package to create elegant nlp pipelines using sklearn.
Home-page: https://github.com/szymonrucinski/pippi-lang
Author: Szymon Ruciński
Keywords: python,stream,sockets
Classifier: Intended Audience :: Developers
Classifier: Programming Language :: Python :: 3
Classifier: Operating System :: Unix
Classifier: Operating System :: MacOS :: MacOS X
Classifier: Operating System :: Microsoft :: Windows
Requires-Dist: scikit-learn
Requires-Dist: nltk
Requires-Dist: pandas
Requires-Dist: coloredlogs
Requires-Dist: beautifulsoup4
Requires-Dist: lxml
